pyramid_webpack/__init__.py
pyramid_webpack/jinja2ext.py
pyramid_webpack-0.1.3.dist-info/DESCRIPTION.rst
pyramid_webpack-0.1.3.dist-info/METADATA
pyramid_webpack-0.1.3.dist-info/RECORD
pyramid_webpack-0.1.3.dist-info/WHEEL
pyramid_webpack-0.1.3.dist-info/metadata.json
pyramid_webpack-0.1.3.dist-info/top_level.txt
