Metadata-Version: 2.0
Name: pyramid-webpack
Version: 0.1.3
Summary: Pyramid extension for managing assets with Webpack.
Home-page: http://github.com/stevearc/pyramid_webpack
Author: Steven Arcangeli
Author-email: stevearc@stevearc.com
License: MIT
Keywords: pyramid webpack assets
Platform: any
Classifier: Development Status :: 4 - Beta
Classifier: Framework :: Pyramid
Classifier: Intended Audience :: Developers
Classifier: License :: OSI Approved :: MIT License
Classifier: Operating System :: OS Independent
Classifier: Programming Language :: Python
Classifier: Programming Language :: Python :: 2
Classifier: Programming Language :: Python :: 2.7
Classifier: Programming Language :: Python :: 3
Classifier: Programming Language :: Python :: 3.4
Classifier: Programming Language :: Python :: 3.5
Classifier: Programming Language :: Python :: 3.6
Requires-Dist: pyramid
Requires-Dist: six (>=1.10.0)
